angel_sdk/__init__.py
angel_sdk/client.py
angel_sdk/exceptions.py
angel_sdk/utils.py
angel_sdk-0.0.1.dist-info/METADATA
angel_sdk-0.0.1.dist-info/WHEEL
angel_sdk-0.0.1.dist-info/top_level.txt
angel_sdk-0.0.1.dist-info/RECORD
