Metadata-Version: 2.1
Name: angel-sdk
Version: 0.0.1
Summary: UNKNOWN
Home-page: UNKNOWN
Author: greene
License: UNKNOWN
Platform: UNKNOWN
Requires-Python: >=3.7
Requires-Dist: requests (>=2.27.1)
